rapdevpy/__init__.py
rapdevpy/concise_numbers.py
rapdevpy/database/__init__.py
rapdevpy/database/convert_to_sql_alchemy_orm.py
rapdevpy/database/sql_alchemy_operator.py
rapdevpy/database/sql_alchemy_tables.py
rapdevpy/database/sqlite_operator.py
rapdevpy/parser/__init__.py
rapdevpy/parser/cprofile_parser.py
rapdevpy/parser/lxml_lib.py
rapdevpy/parser/networkx_lib.py
rapdevpy/profiler.py
rapdevpy/runner.py
rapdevpy/settings.py
rapdevpy-1.0.0.dist-info/entry_points.txt
rapdevpy-1.0.0.dist-info/LICENSE
rapdevpy-1.0.0.dist-info/WHEEL
rapdevpy-1.0.0.dist-info/METADATA
rapdevpy-1.0.0.dist-info/RECORD
