Metadata-Version: 2.1
Name: rapdevpy
Version: 1.0.0
Summary: A (personal) rapid development Python library that manages common tasks, tests and knowledge.
Home-page: https://github.com/MislavJaksic/rapdevpy
License: MIT
Author: Mislav Jaksic
Author-email: jaksicmislav@gmail.com
Requires-Python: >=3.8,<4.0
Classifier: License :: OSI Approved :: MIT License
Classifier: Programming Language :: Python :: 3
Classifier: Programming Language :: Python :: 3.10
Classifier: Programming Language :: Python :: 3.8
Classifier: Programming Language :: Python :: 3.9
Requires-Dist: diskcache (>=5.2.1,<6.0.0)
Requires-Dist: loguru (>=0.6.0,<0.7.0)
Requires-Dist: lxml (>=4.6.2,<5.0.0)
Requires-Dist: networkx (>=2.5.1,<3.0.0)
Requires-Dist: requests (>=2.27.1,<3.0.0)
Requires-Dist: sqlalchemy (>=1.4.22,<2.0.0)
Project-URL: Documentation, https://github.com/MislavJaksic/rapdevpy
Project-URL: Repository, https://github.com/MislavJaksic/rapdevpy
